exercism_api/__init__.py
exercism_api/__main__.py
exercism_api/exercism.py
exercism_api-0.0.1.dist-info/LICENSE
exercism_api-0.0.1.dist-info/METADATA
exercism_api-0.0.1.dist-info/WHEEL
exercism_api-0.0.1.dist-info/top_level.txt
exercism_api-0.0.1.dist-info/RECORD
